{
  "mappings": {
    "bic" : {
      "properties": {
        "indexcreated": { "type" : "date" },
        "indexupdated": { "type" : "date" },
        "identifier": {
          "properties": {
            "type":{
              "type": "text",
              "index": false
            },
            "value":{
              "type": "text",
              "index": false
            },
            "preferred":{ "type": "boolean" }
          }
        },
        "resourcestats": {
          "properties": {
            "views": { "type" : "long" }
          }
        },
        "resourcetype": {
          "type":"text",
          "analyzer": "spanish",
          "search_analyzer": "spanish",
          "fields": {
            "raw": { "type":"keyword" }
          }
        },
        "resourcetitle": {
          "properties": {
            "type":{
              "type": "text",
              "index": false
            },
            "value": {
              "type":"text",
              "analyzer": "spanish",
              "search_analyzer": "spanish"
            }
          }
        },
        "digitalobejct": {
          "properties":{
            "downloads": { "type" : "long"},
            "rights": {
              "properties": {
                "type": {
                  "type": "text",
                  "index": false
                },
                "url": {
                  "type": "text",
                  "index": false
                },
                "rightstitle":{
                  "type": "text",
                  "index": false
                },
                "description": {
                  "type": "text",
                  "index": false
                },
                "holder": {
                  "type": "text",
                  "index": false
                }
              }
            },
            "digitalobjecttitle":{
              "type": "text",
              "index": false
            },
            "url":{
              "type": "text",
              "index": false
            },
            "mediatype": {
              "properties": {
                "name" : {
                  "type": "text",
                  "analyzer": "spanish",
                  "search_analyzer": "spanish",
                  "fields": {
                    "raw": { "type":"keyword" }
                  }
                },
                "mime": {
                  "type": "text",
                  "index": false
                }
              }
            }
          }
        },
        "rights": {
          "properties": {
            "type": {
              "type": "text",
              "index": false
            },
            "url": {
              "type": "text",
              "index": false
            },
            "rightstitle":{
              "type": "text",
              "index": false
            },
            "description": {
              "type": "text",
              "index": false
            },
            "holder": {
              "type": "text",
              "index": false
            }
          }
        },
        "creator": {
          "type" : "text",
          "analyzer": "spanish",
          "search_analyzer": "spanish",
          "fields" : {
            "raw" : { "type" : "keyword" }
          }
        },
        "datecreated": {
          "properties": {
            "format": {
              "type": "text",
              "index": false
            },
            "value": {
              "type": "date",
              "fields": {
                "textvalue": { "type" : "text" }
              }
            }
          }
        },
        "periodcreated": {
          "properties": {
            "name": {
              "type": "text",
              "analyzer": "spanish",
              "search_analyzer": "spanish",
              "fields": {
                "raw": { "type":"keyword" }
              }
            },
            "datestart": {
              "properties": {
                "format": {
                  "type": "text",
                  "index": false
                },
                "value": { "type": "date" }
              }
            },
            "dateend": {
              "properties": {
                "format": {
                  "type": "text",
                  "index": false
                },
                "value": { "type": "date" }
              }
            }
          }
        },
        "holder" : {
          "type" : "text",
          "analyzer": "spanish",
          "search_analyzer": "spanish",
          "fields": {
            "raw": { "type": "keyword" }
          }
        },
        "catchall": { "type" : "text"}
      }
    }
  },
  "settings": {
    "index": {
      "analysis": {
        "analyzer": {
          "nfkc_cf_normalized": {
            "tokenizer": "icu_tokenizer",
            "char_filter": [
              "icu_normalizer"
            ]
          },
          "nfd_normalized": {
            "tokenizer": "icu_tokenizer",
            "char_filter": [
              "nfd_normalizer"
            ]
          }
        },
        "char_filter": {
          "nfd_normalizer": {
            "type": "icu_normalizer",
            "name": "nfc",
            "mode": "decompose"
          }
        }
      }
    }
  }
}